{
  "id": 1325,
  "address": "Badweg, Nieuwkuijk",
  "placename": "Nieuwkuijk",
  "description": "Nieuwkuijkse Wiel of de Nieuwe Wiel ligt in het groen aan de Badweg.  Alleen de noordoostelijke inham wordt gebruikt als zwemlocatie.",
  "photos": "NB-047-001 Nieuwkuykse Wiel.jpg",
  "website": null,
  "alternate_name": "Nieuwkuijkse Wiel",
  "name": "Nieuwkuijkse Wiel",
  "current_status": "goed",
  "lat": 51.6887,
  "lon": 5.187,
  "eu_designation": "1",
  "e_coli": 30.0,
  "int_ent": 15.0,
  "amenities": [],
  "warnings": []
}