{
  "id": 1344,
  "address": "Paralelleweg, Tynaarlo",
  "placename": "Tynaarlo",
  "description": "De zwemlocatie \u201ft Veenmeer is gelegen in Tynaarlo. De zwemlocatie \u201ft Veenmeer is een ge\u00efsoleerde plas en heeft een  omvang van 100 bij 300 meter en een diepte van max. 18 meter",
  "photos": "Recreatiezone_'t_Veenmeer.jpg",
  "website": null,
  "alternate_name": "'t Veenmeer",
  "name": "'t Veenmeer",
  "current_status": "goed",
  "lat": 53.0829,
  "lon": 6.6303,
  "eu_designation": "1",
  "e_coli": 15.0,
  "int_ent": 15.0,
  "amenities": [
    5943906,
    5943907,
    5943895,
    5943911,
    5943913,
    5943916,
    5943897,
    5943891,
    5943892,
    5943893,
    5943898,
    5943927,
    5943896,
    5943929,
    5943930,
    5943900,
    5943901,
    5943902
  ],
  "warnings": []
}