{
  "id": 1432,
  "address": "Spijkweg, Biddinghuizen",
  "placename": "Biddinghuizen",
  "description": "De Spijkvijver ligt midden in het Spijkbos in Flevoland, circa 5 km ten oosten van Biddinghuizen, vlakbij het Veluwemeer en Walibi world. De vijver bestaat uit twee plassen die via een versmalling met elkaar in verbinding staan. De oppervlakte van de beide plassen samen bedraagt ruim 3 hectare en de waterdiepte is circa 1,5 meter. Het zwemstrand is gelegen aan de westelijke plas en heeft ook een grote ligweide. Gedurende de zomerperiode zakt de waterstand in de plas sterk tot wel 40 - 50 cm diep.",
  "photos": "DOCUVITP-#1332276-v1-12_068_Spijkstrand_1_pdf.jpg",
  "website": "http://www.buitencentra.nl/Home/Natuurgebieden/Randmeerbossen.aspx?tab=Toegankelijkheid",
  "alternate_name": "Spijkstrand",
  "name": "Spijkvijver, Biddinghuizen",
  "current_status": "goed",
  "lat": 52.4497,
  "lon": 5.7741,
  "eu_designation": "1",
  "e_coli": 1007.0,
  "int_ent": 15.0,
  "amenities": [
    5943907,
    5943911,
    5943895,
    5943929,
    5943930
  ],
  "warnings": []
}