{
  "id": 1437,
  "address": "Rijksweg 15 a, Heel",
  "placename": "Heel",
  "description": "De Heelderpeel is een recreatiepark met eigen strand aan een meertje.",
  "photos": "Dagstrand Heelderpeel.JPG",
  "website": null,
  "alternate_name": "Dagstrand Peel Beach Heelderpeel",
  "name": "Dagstrand Peel Beach Heelderpeel",
  "current_status": "goed",
  "lat": 51.1975,
  "lon": 5.8855,
  "eu_designation": "1",
  "e_coli": 61.0,
  "int_ent": 110.0,
  "amenities": [
    5943907,
    5943911,
    5943892,
    5943898,
    5943927,
    5943929,
    5943930,
    5943932,
    5943902
  ],
  "warnings": []
}